LICENSE
MANIFEST.in
README.md
requirements.txt
setup.py
NotionDump/__init__.py
NotionDump/Dump/__init__.py
NotionDump/Dump/block.py
NotionDump/Dump/database.py
NotionDump/Dump/dump.py
NotionDump/Dump/page.py
NotionDump/Notion/Buffer.py
NotionDump/Notion/Notion.py
NotionDump/Notion/__init__.py
NotionDump/Parser/__init__.py
NotionDump/Parser/base_parser.py
NotionDump/Parser/block_parser.py
NotionDump/Parser/database_parser.py
NotionDump/Parser/mix_parser.py
NotionDump/utils/__init__.py
NotionDump/utils/common_op.py
NotionDump/utils/content_format.py
NotionDump/utils/internal_var.py
examples/block_dump.py
examples/db_dump.py
examples/page_dump.py
notion_dump_kernel.egg-info/PKG-INFO
notion_dump_kernel.egg-info/SOURCES.txt
notion_dump_kernel.egg-info/dependency_links.txt
notion_dump_kernel.egg-info/requires.txt
notion_dump_kernel.egg-info/top_level.txt