Metadata-Version: 2.1
Name: notion-dump-kernel
Version: 0.2.3
Summary: Freely available tools for export Notion page and database.
Home-page: https://github.com/delta1037/notion-export-kernel
Author: delta1037
Author-email: geniusrabbit@qq.com
License: UNKNOWN
Project-URL: Documentation, https://github.com/delta1037/notion-export-kernel/blob/main/README.md
Project-URL: Source, https://github.com/delta1037/notion-export-kernel
Project-URL: Tracker, https://github.com/delta1037/notion-export-kernel/issues
Platform: UNKNOWN
Classifier: Development Status :: 3 - Alpha
Classifier: Intended Audience :: Developers
Classifier: License :: OSI Approved :: MIT License
Classifier: Operating System :: OS Independent
Classifier: Programming Language :: Python
Classifier: Programming Language :: Python :: 3.9
Classifier: Topic :: Text Processing :: Markup
Classifier: Topic :: Software Development :: Libraries :: Python Modules
License-File: LICENSE
